Taowa_web3/__init__.py
Taowa_web3/taowa_web3.py
Taowa_web3-1.0.1.dist-info/METADATA
Taowa_web3-1.0.1.dist-info/WHEEL
Taowa_web3-1.0.1.dist-info/top_level.txt
Taowa_web3-1.0.1.dist-info/RECORD
