Metadata-Version: 2.1
Name: Taowa_web3
Version: 1.0.1
Author: 
Author-email: 
Classifier: Programming Language :: Python :: 3
Classifier: License :: OSI Approved :: MIT License
Classifier: Operating System :: OS Independent
Requires-Python: >=3.6
Requires-Dist: web3
